{"name":"Mask Network","logoURI":"https://raw.githubusercontent.com/DimensionDev/Maskbook-Website/master/img/MB--CircleCanvas--WhiteOverBlue.svg","keywords":["browser extension","web3","peer to peer","encryption","cryptography","gundb","privacy protection","ownyourdata","social network","blockchain","crypto","dweb"],"timestamp":"2023-10-24T00:22:02.501Z","version":{"major":0,"minor":0,"patch":65},"tokens":[{"name":"Aave","symbol":"AAVE","address":"0x79379C0E09a41d7978f883a56246290eE9a8c4d3","chainId":534352,"decimals":18,"logoURI":"https://scroll-tech.github.io/token-list/data/AAVE/logo.svg"},{"name":"Balancer","symbol":"BAL","address":"0x6a28e90582c583fcd3347931c544819C31e9D0e0","chainId":534352,"decimals":18,"logoURI":"https://scroll-tech.github.io/token-list/data/BAL/logo.png"},{"name":"PancakeSwap","symbol":"CAKE","address":"0xF613F403C2887aa473b46252da3AA5D6a6084b15","chainId":534352,"decimals":18,"logoURI":"https://scroll-tech.github.io/token-list/data/CAKE/logo.svg"},{"name":"Curve DAO","symbol":"CRV","address":"0xB755039eDc7910C1F1BD985D48322E55A31AC0bF","chainId":534352,"decimals":18,"logoURI":"https://scroll-tech.github.io/token-list/data/CRV/logo.png"},{"name":"Dai","symbol":"DAI","address":"0xcA77eB3fEFe3725Dc33bccB54eDEFc3D9f764f97","chainId":534352,"decimals":18,"logoURI":"https://scroll-tech.github.io/token-list/data/DAI/logo.svg"},{"name":"Kyber Network Crystal","symbol":"KNC","address":"0x608ef9A3BffE206B86c3108218003b3cfBf99c84","chainId":534352,"decimals":18,"logoURI":"https://scroll-tech.github.io/token-list/data/KNC/logo.svg"},{"name":"Liquity USD","symbol":"LUSD","address":"0xeDEAbc3A1e7D21fE835FFA6f83a710c70BB1a051","chainId":534352,"decimals":18,"logoURI":"https://scroll-tech.github.io/token-list/data/LUSD/logo.svg"},{"name":"Rocket Pool ETH","symbol":"rETH","address":"0x53878B874283351D26d206FA512aEcE1Bef6C0dD","chainId":534352,"decimals":18,"logoURI":"https://scroll-tech.github.io/token-list/data/rETH/logo.svg"},{"name":"Uniswap","symbol":"UNI","address":"0x434cdA25E8a2CA5D9c1C449a8Cb6bCbF719233E8","chainId":534352,"decimals":18,"logoURI":"https://scroll-tech.github.io/token-list/data/UNI/logo.png"},{"name":"USD Coin","symbol":"USDC","address":"0x06eFdBFf2a14a7c8E15944D1F4A48F9F95F663A4","chainId":534352,"decimals":6,"logoURI":"https://scroll-tech.github.io/token-list/data/USDC/logo.svg"},{"name":"Tether","symbol":"USDT","address":"0xf55BEC9cafDbE8730f096Aa55dad6D22d44099Df","chainId":534352,"decimals":6,"logoURI":"https://scroll-tech.github.io/token-list/data/USDT/logo.svg"},{"name":"Wrapped BTC","symbol":"WBTC","address":"0x3C1BCa5a656e69edCD0D4E36BEbb3FcDAcA60Cf1","chainId":534352,"decimals":8,"logoURI":"https://scroll-tech.github.io/token-list/data/WBTC/logo.svg"},{"name":"Wrapped Ether","symbol":"WETH","address":"0x5300000000000000000000000000000000000004","chainId":534352,"decimals":18,"logoURI":"https://scroll-tech.github.io/token-list/data/WETH/logo.png"},{"name":"Wrapped stETH","symbol":"wstETH","address":"0xf610A9dfB7C89644979b4A0f27063E9e7d7Cda32","chainId":534352,"decimals":18,"logoURI":"https://scroll-tech.github.io/token-list/data/wstETH/logo.svg"}]}